{
	"vowels": ["ᜀ", "ᜀ", "ᜁ", "ᜁ", "ᜂ", "ᜂ", "ᜎᜓ", "ᜎᜓ", "ᜎᜓ", "ᜎᜓ", "ᜁ", "ᜁ", "ᜀᜁ", "ᜂ", "ᜂ", "ᜀᜂ"],
	"vowel_marks": ["", "ᜒ", "ᜒ", "ᜓ", "ᜓ", "᜔ᜎᜓ", "᜔ᜎᜓ", "᜔ᜎᜓ", "᜔ᜎᜓ", "ᜒ", "ᜒ", "ᜁ", "ᜓ", "ᜓ", "ᜂ"],
	"other_marks": ["ᜋ᜔", "ᜑ᜔", "ᜋ᜔"],
	"virama": ["᜔"],
	"consonants": ["ᜃ", "ᜃ", "ᜄ", "ᜄ", "ᜅ", "ᜐ", "ᜐ", "ᜇ", "ᜇ", "ᜈ", "ᜆ", "ᜆ", "ᜇ", "ᜇ", "ᜈ", "ᜆ", "ᜆ", "ᜇ", "ᜇ", "ᜈ", "ᜉ", "ᜉ", "ᜊ", "ᜊ", "ᜋ", "ᜌ", "ᜎ", "ᜎ", "ᜏ", "ᜐ", "ᜐ", "ᜐ", "ᜑ", "ᜎ", "ᜃ᜔ᜐ", "ᜇ᜔ᜈ"],
	"symbols": ["0", "1", "2", "3", "4", "5", "6", "7", "8", "9", "ᜂᜋ᜔", "", "᜵", "᜶"],
	"candra": ["ᜒ"],
	"other": ["ᜃ", "ᜃ", "ᜄ", "ᜇ", "ᜇ", "ᜇ", "ᜉ", "ᜌ", "ᜎ"]
}
